src/__init__.py
src/thread_manage.py
thread_manage/__init__.py
thread_manage/thread_manage.py
PyThreadManage-0.5.dist-info/LICENSE
PyThreadManage-0.5.dist-info/METADATA
PyThreadManage-0.5.dist-info/WHEEL
PyThreadManage-0.5.dist-info/top_level.txt
PyThreadManage-0.5.dist-info/RECORD
