Metadata-Version: 2.1
Name: PyThreadManage
Version: 0.5
Summary: encapsulate functions of thread module
Home-page: https://github.com/chihuen/PyThreadManage
Author: Chihuen Lau
Author-email: chihuenlau@gmail.com
License: MIT Licence
Platform: UNKNOWN
